honcho/__init__.py
honcho/__main__.py
honcho/_version.py
honcho/colour.py
honcho/command.py
honcho/compat.py
honcho/environ.py
honcho/manager.py
honcho/printer.py
honcho/process.py
honcho/export/__init__.py
honcho/export/base.py
honcho/export/runit.py
honcho/export/supervisord.py
honcho/export/systemd.py
honcho/export/upstart.py
honcho/export/templates/runit/run
honcho/export/templates/runit/log/run
honcho/export/templates/supervisord/supervisord.conf
honcho/export/templates/systemd/master.target
honcho/export/templates/systemd/process.service
honcho/export/templates/systemd/process_master.target
honcho/export/templates/upstart/master.conf
honcho/export/templates/upstart/process.conf
honcho/export/templates/upstart/process_master.conf
honcho-2.0.0.dist-info/AUTHORS.rst
honcho-2.0.0.dist-info/LICENSE
honcho-2.0.0.dist-info/METADATA
honcho-2.0.0.dist-info/WHEEL
honcho-2.0.0.dist-info/entry_points.txt
honcho-2.0.0.dist-info/top_level.txt
honcho-2.0.0.dist-info/RECORD
