Metadata-Version: 2.1
Name: honcho
Version: 2.0.0
Summary: Honcho: a Python clone of Foreman. For managing Procfile-based applications.
Author-email: Nick Stenning <nick@whiteink.com>
Project-URL: Source, https://github.com/nickstenning/honcho
Keywords: sysadmin,process,procfile
Classifier: Environment :: Console
Classifier: Intended Audience :: Developers
Classifier: Intended Audience :: System Administrators
Classifier: License :: OSI Approved :: MIT License
Classifier: Operating System :: OS Independent
Classifier: Programming Language :: Python
Classifier: Programming Language :: Python :: 3
Classifier: Programming Language :: Python :: 3.8
Classifier: Programming Language :: Python :: 3.9
Classifier: Programming Language :: Python :: 3.10
Classifier: Programming Language :: Python :: 3.11
Classifier: Programming Language :: Python :: 3.12
Classifier: Programming Language :: Python :: 3.13
Classifier: Programming Language :: Python :: Implementation :: CPython
Classifier: Programming Language :: Python :: Implementation :: PyPy
License-File: LICENSE
License-File: AUTHORS.rst
Requires-Dist: backports.entry-points-selectable; python_version < "3.10"
Requires-Dist: colorama; sys_platform == "win32"
Provides-Extra: export
Requires-Dist: jinja2<4,>=3.1.2; extra == "export"
Provides-Extra: docs
Requires-Dist: sphinx; extra == "docs"
